ctfbox/__init__.py
ctfbox/crypto/__init__.py
ctfbox/crypto/crypto.py
ctfbox/exceptions/__init__.py
ctfbox/exceptions/exceptions.py
ctfbox/main.py
ctfbox/misc/__init__.py
ctfbox/misc/misc.py
ctfbox/pwn/__init__.py
ctfbox/pwn/pwn.py
ctfbox/pwntools/__init__.py
ctfbox/pwntools/config.py
ctfbox/reverse/__init__.py
ctfbox/reverse/reverse.py
ctfbox/tests/__init__.py
ctfbox/tests/crypto_test.py
ctfbox/tests/misc_test.py
ctfbox/tests/php_serialize_test.py
ctfbox/tests/pwn_test.py
ctfbox/tests/reverse_test.py
ctfbox/tests/utils_test.py
ctfbox/tests/web_test.py
ctfbox/thirdparty/__init__.py
ctfbox/thirdparty/dict/bak.txt
ctfbox/thirdparty/dsstore.py
ctfbox/thirdparty/gin.py
ctfbox/thirdparty/phpserialize.py
ctfbox/thirdparty/redis/exp.so
ctfbox/thirdparty/reverse_mtrand.py
ctfbox/utils/__init__.py
ctfbox/utils/utils.py
ctfbox/web/__init__.py
ctfbox/web/fpm.py
ctfbox/web/web.py
ctfbox-1.12.5.dist-info/WHEEL
ctfbox-1.12.5.dist-info/METADATA
ctfbox-1.12.5.dist-info/licenses/LICENSE
ctfbox-1.12.5.dist-info/RECORD
