Metadata-Version: 2.1
Name: ctfbox
Version: 1.12.5
Summary: A box for CTF challenges with some sugar functions, Just enjoy it
License: MIT
Author: Syclover
Author-email: Longlone <toloveu29@gmail.com>,pjx <pjx3231@163.com>,lingze <lingze.wl@gmail.com>,F4ded <452584023@qq.com>,AFKL <afkl1919@qq.com>
Requires-Python: >=3.7
Requires-Dist: PyJWT<3.0.0,>=2.0.1
Requires-Dist: requests<3.0.0,>=2.25.1
Project-URL: homepage, https://github.com/WAY29/ctfbox
